{"slug":"revenges-eye","name":"Revenge's Eye","desc":"You touch a creature's visual organs and grant them the ability to see the trail left by creatures damaged by a weapon you cast invisible creatures; it only reveals trails left by those affected by order of revenge also cast by the spellcaster.","higher_level":"When you cast this spell using a spell slot of 3rd level or higher, you can target +1 creature for each slot level above second.","range":"Touch","components":"V, S, M","ritual":"no","duration":"1 Hour","concentration":"no","casting_time":"1 action","level_int":2}